.DS_Store
geometry_lab/.DS_Store
geometry_lab/__init__.py
geometry_lab/point.py
geometry_lab/figures/__init__.py
geometry_lab/figures/line.py
geometry_lab/figures/triangle.py
geometry_lab-1.0.dist-info/METADATA
geometry_lab-1.0.dist-info/WHEEL
geometry_lab-1.0.dist-info/top_level.txt
geometry_lab-1.0.dist-info/RECORD
