Metadata-Version: 2.1
Name: geometry_lab
Version: 1.0
Summary: This  is very useful package
Home-page: UNKNOWN
Author: orbly
Author-email: orblymusic@gmail.com
License: UNKNOWN
Platform: UNKNOWN
